{
	"configurations" : 
	[
		{
			"directories" : 
			[
				{
					"build" : ".",
					"jsonFile" : "directory-.-Debug-f5ebdc15457944623624.json",
					"minimumCMakeVersion" : 
					{
						"string" : "3.22"
					},
					"projectIndex" : 0,
					"source" : ".",
					"targetIndexes" : 
					[
						0,
						1
					]
				}
			],
			"name" : "Debug",
			"projects" : 
			[
				{
					"directoryIndexes" : 
					[
						0
					],
					"name" : "Space-Dance",
					"targetIndexes" : 
					[
						0,
						1
					]
				}
			],
			"targets" : 
			[
				{
					"directoryIndex" : 0,
					"id" : "Space-Dance::@6890427a1f51a3e7e1df",
					"jsonFile" : "target-Space-Dance-Debug-62ac73dc3a60a743b994.json",
					"name" : "Space-Dance",
					"projectIndex" : 0
				},
				{
					"directoryIndex" : 0,
					"id" : "run::@6890427a1f51a3e7e1df",
					"jsonFile" : "target-run-Debug-22c975fa0ca1f90fcc52.json",
					"name" : "run",
					"projectIndex" : 0
				}
			]
		}
	],
	"kind" : "codemodel",
	"paths" : 
	{
		"build" : "/home/javad/VSC/Space-Dance/build",
		"source" : "/home/javad/VSC/Space-Dance"
	},
	"version" : 
	{
		"major" : 2,
		"minor" : 3
	}
}
